{
  "type": "component",
  "metadata": {},
  "schema": {
    "name": "metaData-container",
    "friendlyName": "metaData-container",
    "description": "container normal qui envoie dans le <head> ses informations",
    "icon": "RectSelect",
    "hasChildren": true,
    "settings": [
      {
        "type": "text",
        "key": "title",
        "label": "title"
      },
      {
        "type": "text",
        "key": "meta_description",
        "label": "meta description"
      }
    ]
  },
  "hash": "6b866f02646f405db864b181142e366d85d13c2c",
  "version": "1.0.3"
}